easysave/__init__.py
easysaveservice-0.2.3.dist-info/licenses/LICENSE
easysaveservice-0.2.3.dist-info/METADATA
easysaveservice-0.2.3.dist-info/WHEEL
easysaveservice-0.2.3.dist-info/top_level.txt
easysaveservice-0.2.3.dist-info/RECORD
