Metadata-Version: 2.4
Name: EasySaveService
Version: 0.2.3
Summary: EasySave service python library
Home-page: https://github.com/DavComo/EasySaveModule
Author: David Comor
Author-email: david.comor@gmail.com
Classifier: Programming Language :: Python :: 3
Classifier: License :: OSI Approved :: MIT License
Classifier: Operating System :: OS Independent
License-File: LICENSE
Requires-Dist: requests
Dynamic: author
Dynamic: author-email
Dynamic: classifier
Dynamic: description
Dynamic: description-content-type
Dynamic: home-page
Dynamic: license-file
Dynamic: requires-dist
Dynamic: summary
